{
  "steny": [
    {
      "id": "W1",
      "od": [
        12.28785,
        -4.2334
      ],
      "do": [
        6.6024,
        -4.2334
      ],
      "tloustka": 0.15,
      "typ": "pricka",
      "od_constraint": null,
      "do_constraint": null
    },
    {
      "id": "W2",
      "od": [
        12.28785,
        -0.3019
      ],
      "do": [
        12.28785,
        -4.2334
      ],
      "tloustka": 0.23769999999999983,
      "typ": "obvodova",
      "od_constraint": null,
      "do_constraint": null
    },
    {
      "id": "W3",
      "od": [
        0.5749000000000001,
        -0.3019
      ],
      "do": [
        12.28785,
        -0.3019
      ],
      "tloustka": 0.298,
      "typ": "nosna",
      "od_constraint": null,
      "do_constraint": null
    },
    {
      "id": "W4",
      "od": [
        0.5749000000000001,
        -9.2552
      ],
      "do": [
        0.5749000000000001,
        -0.3019
      ],
      "tloustka": 0.24799999999999997,
      "typ": "nosna",
      "od_constraint": null,
      "do_constraint": null
    },
    {
      "id": "W5",
      "od": [
        2.7848,
        -9.2552
      ],
      "do": [
        0.5749000000000001,
        -9.2552
      ],
      "tloustka": 0.15,
      "typ": "pricka",
      "od_constraint": null,
      "do_constraint": null
    },
    {
      "id": "W6",
      "od": [
        2.7848,
        -9.2552
      ],
      "do": [
        2.7848,
        -7.417000000000001
      ],
      "tloustka": 0.15000000000000002,
      "typ": "pricka",
      "od_constraint": null,
      "do_constraint": null
    },
    {
      "id": "W7",
      "od": [
        2.7848,
        -7.417000000000001
      ],
      "do": [
        6.6024,
        -7.417000000000001
      ],
      "tloustka": 0.15,
      "typ": "pricka",
      "od_constraint": null,
      "do_constraint": null
    },
    {
      "id": "W8",
      "od": [
        6.6024,
        -7.417000000000001
      ],
      "do": [
        6.6024,
        -4.2334
      ],
      "tloustka": 0.15000000000000002,
      "typ": "pricka",
      "od_constraint": null,
      "do_constraint": null
    },
    {
      "id": "W9",
      "od": [
        2.7098000000000004,
        -7.417000000000001
      ],
      "do": [
        0.6989,
        -7.417000000000001
      ],
      "tloustka": 0.15,
      "typ": "pricka",
      "od_constraint": {
        "host": "W6",
        "t": 1.0
      },
      "do_constraint": {
        "host": "W4",
        "t": 0.2053
      }
    },
    {
      "id": "W10",
      "od": [
        6.9441999999999995,
        -4.158399999999999
      ],
      "do": [
        6.9441999999999995,
        -0.4509
      ],
      "tloustka": 0.1,
      "typ": "pricka",
      "od_constraint": {
        "host": "W1",
        "t": 0.9399
      },
      "do_constraint": {
        "host": "W3",
        "t": 0.5438
      }
    },
    {
      "id": "W11",
      "od": [
        4.9298,
        -0.4509
      ],
      "do": [
        4.9298,
        -7.3420000000000005
      ],
      "tloustka": 0.1,
      "typ": "pricka",
      "od_constraint": {
        "host": "W3",
        "t": 0.3718
      },
      "do_constraint": {
        "host": "W7",
        "t": 0.5619
      }
    },
    {
      "id": "W12",
      "od": [
        0.6989,
        -4.2248
      ],
      "do": [
        4.8798,
        -4.2248
      ],
      "tloustka": 0.1624000000000001,
      "typ": "pricka",
      "od_constraint": {
        "host": "W4",
        "t": 0.5618
      },
      "do_constraint": {
        "host": "W11",
        "t": 0.5457
      }
    },
    {
      "id": "W13",
      "od": [
        4.9798,
        -2.9622
      ],
      "do": [
        6.8942,
        -2.9622
      ],
      "tloustka": 0.10000000000000002,
      "typ": "pricka",
      "od_constraint": {
        "host": "W11",
        "t": 0.3701
      },
      "do_constraint": {
        "host": "W10",
        "t": 0.3359
      }
    },
    {
      "id": "W14",
      "od": [
        12.4067,
        -4.2184
      ],
      "do": [
        14.0259,
        -4.2184
      ],
      "tloustka": 0.18,
      "typ": "pricka",
      "od_constraint": {
        "host": "W2",
        "t": 0.9962
      },
      "do_constraint": null
    },
    {
      "id": "W15",
      "od": [
        12.4067,
        -0.37090000000000006
      ],
      "do": [
        14.0259,
        -0.37090000000000006
      ],
      "tloustka": 0.16000000000000003,
      "typ": "pricka",
      "od_constraint": {
        "host": "W2",
        "t": 0.0176
      },
      "do_constraint": null
    }
  ],
  "otvory": [
    {
      "id": "O1",
      "stena": "W2",
      "pozice": 0.6351000000000001,
      "sirka": 1.7966000000000002,
      "typ": "okno",
      "smer_otvirani": null,
      "pocet_kridel": 1,
      "typ_dveri": null
    },
    {
      "id": "D1",
      "stena": "W2",
      "pozice": 2.5048000000000004,
      "sirka": 0.8038999999999998,
      "typ": "dvere",
      "smer_otvirani": "right_out",
      "pocet_kridel": 1,
      "typ_dveri": "jednostranne"
    },
    {
      "id": "O2",
      "stena": "W3",
      "pozice": 4.4313,
      "sirka": 0.5960000000000002,
      "typ": "okno",
      "smer_otvirani": null,
      "pocet_kridel": 1,
      "typ_dveri": null
    },
    {
      "id": "O3",
      "stena": "W4",
      "pozice": 5.7005,
      "sirka": 1.8066000000000009,
      "typ": "okno",
      "smer_otvirani": null,
      "pocet_kridel": 1,
      "typ_dveri": null
    },
    {
      "id": "O4",
      "stena": "W4",
      "pozice": 2.4804999999999997,
      "sirka": 1.8333000000000004,
      "typ": "okno",
      "smer_otvirani": null,
      "pocet_kridel": 1,
      "typ_dveri": null
    },
    {
      "id": "D2",
      "stena": "W7",
      "pozice": 2.4004,
      "sirka": 0.8194000000000006,
      "typ": "dvere",
      "smer_otvirani": "right_out",
      "pocet_kridel": 1,
      "typ_dveri": "obouchodne"
    },
    {
      "id": "D3",
      "stena": "W9",
      "pozice": 0.5309000000000004,
      "sirka": 0.6311999999999998,
      "typ": "dvere",
      "smer_otvirani": "right_in",
      "pocet_kridel": 1,
      "typ_dveri": "jednostranne"
    },
    {
      "id": "D4",
      "stena": "W10",
      "pozice": 0.0892999999999995,
      "sirka": 0.8145000000000004,
      "typ": "dvere",
      "smer_otvirani": "left_in",
      "pocet_kridel": 1,
      "typ_dveri": "jednostranne"
    },
    {
      "id": "D5",
      "stena": "W11",
      "pozice": 6.006799999999999,
      "sirka": 0.8027999999999997,
      "typ": "dvere",
      "smer_otvirani": "right_in",
      "pocet_kridel": 1,
      "typ_dveri": "jednostranne"
    },
    {
      "id": "D6",
      "stena": "W11",
      "pozice": 2.8083000000000005,
      "sirka": 0.8327999999999998,
      "typ": "dvere",
      "smer_otvirani": "right_in",
      "pocet_kridel": 1,
      "typ_dveri": "jednostranne"
    },
    {
      "id": "D7",
      "stena": "W13",
      "pozice": 0.6610000000000003,
      "sirka": 0.7001,
      "typ": "dvere",
      "smer_otvirani": "right_in",
      "pocet_kridel": 1,
      "typ_dveri": "jednostranne"
    }
  ],
  "prostory": [
    {
      "id": "P1",
      "typ": "Outdoor",
      "podtyp": null,
      "polygon": [
        [
          12.4067,
          -0.4509
        ],
        [
          13.925899999999999,
          -0.4509
        ],
        [
          13.925899999999999,
          -4.1284
        ],
        [
          12.4067,
          -4.1284
        ],
        [
          12.4067,
          -0.4509
        ],
        [
          12.4067,
          -0.4509
        ]
      ],
      "plocha_m2": 5.59,
      "nazev": "ULKOTILA",
      "venkovni": true
    },
    {
      "id": "P2",
      "typ": "LivingRoom",
      "podtyp": null,
      "polygon": [
        [
          12.169,
          -4.158399999999999
        ],
        [
          6.994199999999999,
          -4.158399999999999
        ],
        [
          6.994199999999999,
          -0.4509
        ],
        [
          12.169,
          -0.4509
        ]
      ],
      "plocha_m2": 19.19,
      "nazev": "OH",
      "venkovni": false
    },
    {
      "id": "P3",
      "typ": "Kitchen",
      "podtyp": null,
      "polygon": [
        [
          4.8798,
          -4.1436
        ],
        [
          0.6989,
          -4.1436
        ],
        [
          0.6989,
          -0.4509
        ],
        [
          4.8798,
          -0.4509
        ]
      ],
      "plocha_m2": 15.44,
      "nazev": "K",
      "venkovni": false
    },
    {
      "id": "P4",
      "typ": "Bedroom",
      "podtyp": null,
      "polygon": [
        [
          4.8798,
          -7.3420000000000005
        ],
        [
          0.6989,
          -7.3420000000000005
        ],
        [
          0.6989,
          -4.306
        ],
        [
          4.8798,
          -4.306
        ]
      ],
      "plocha_m2": 12.69,
      "nazev": "MH",
      "venkovni": false
    },
    {
      "id": "P5",
      "typ": "Undefined",
      "podtyp": null,
      "polygon": [
        [
          6.8942,
          -4.158399999999999
        ],
        [
          6.5274,
          -4.158399999999999
        ],
        [
          6.5274,
          -7.3420000000000005
        ],
        [
          4.9798,
          -7.3420000000000005
        ],
        [
          4.9798,
          -3.0122000000000004
        ],
        [
          6.8942,
          -3.0122000000000004
        ]
      ],
      "plocha_m2": 7.12,
      "nazev": "UNDEFINED",
      "venkovni": false
    },
    {
      "id": "P6",
      "typ": "Bath",
      "podtyp": null,
      "polygon": [
        [
          6.8942,
          -2.9122000000000003
        ],
        [
          4.9798,
          -2.9122000000000003
        ],
        [
          4.9798,
          -0.4509
        ],
        [
          6.8942,
          -0.4509
        ]
      ],
      "plocha_m2": 4.71,
      "nazev": "KH",
      "venkovni": false
    },
    {
      "id": "P7",
      "typ": "Closet",
      "podtyp": "WalkIn",
      "polygon": [
        [
          2.7098000000000004,
          -9.1802
        ],
        [
          0.6989,
          -9.1802
        ],
        [
          0.6989,
          -7.492000000000001
        ],
        [
          2.7098000000000004,
          -7.492000000000001
        ]
      ],
      "plocha_m2": 3.39,
      "nazev": "VH",
      "venkovni": false
    }
  ],
  "vybaveni": [
    {
      "id": "V1",
      "typ": "Housing",
      "podtyp": null,
      "kategorie": "ostatni",
      "stred": [
        0.7808490000000002,
        -0.7508520000000002
      ],
      "polygon": [
        [
          0.698904,
          -0.45085200000000003
        ],
        [
          0.862794,
          -0.45085200000000003
        ],
        [
          0.862794,
          -1.0508520000000001
        ],
        [
          0.698904,
          -1.0508520000000001
        ]
      ],
      "sirka": 0.164,
      "hloubka": 0.6,
      "tvar": "rect",
      "uhel": 0.0,
      "zadni_strana": null,
      "vyska": 2.0,
      "elevation": 0.0
    },
    {
      "id": "V2",
      "typ": "Closet",
      "podtyp": null,
      "kategorie": "uloziste",
      "stred": [
        1.178844,
        -0.7521030000000001
      ],
      "polygon": [
        [
          0.862794,
          -0.452103
        ],
        [
          1.494894,
          -0.452103
        ],
        [
          1.494894,
          -1.052103
        ],
        [
          0.862794,
          -1.052103
        ]
      ],
      "sirka": 0.632,
      "hloubka": 0.6,
      "tvar": "rect",
      "uhel": 0.0,
      "zadni_strana": null,
      "vyska": 2.0,
      "elevation": 0.0
    },
    {
      "id": "V3",
      "typ": "ElectricalAppliance",
      "podtyp": "Refrigerator",
      "kategorie": "kuchyn",
      "stred": [
        1.794847,
        -0.7521020000000002
      ],
      "polygon": [
        [
          1.494847,
          -0.452102
        ],
        [
          2.094847,
          -0.452102
        ],
        [
          2.094847,
          -1.052102
        ],
        [
          1.494847,
          -1.052102
        ]
      ],
      "sirka": 0.6,
      "hloubka": 0.6,
      "tvar": "rect",
      "uhel": 0.0,
      "zadni_strana": null,
      "vyska": 1.7,
      "elevation": 0.0
    },
    {
      "id": "V4",
      "typ": "BaseCabinet",
      "podtyp": null,
      "kategorie": "kuchyn",
      "stred": [
        3.185147,
        -0.752572
      ],
      "polygon": [
        [
          2.094847,
          -0.452572
        ],
        [
          4.275447000000001,
          -0.452572
        ],
        [
          4.275447000000001,
          -1.052572
        ],
        [
          2.094847,
          -1.052572
        ]
      ],
      "sirka": 2.181,
      "hloubka": 0.6,
      "tvar": "rect",
      "uhel": 0.0,
      "zadni_strana": "west",
      "vyska": 0.9,
      "elevation": 0.0
    },
    {
      "id": "V5",
      "typ": "BaseCabinet",
      "podtyp": null,
      "kategorie": "kuchyn",
      "stred": [
        4.5775950000000005,
        -1.8794019999999998
      ],
      "polygon": [
        [
          4.877595,
          -1.052102
        ],
        [
          4.877595,
          -2.7067020000000004
        ],
        [
          4.277595,
          -2.7067020000000004
        ],
        [
          4.277595,
          -1.052102
        ]
      ],
      "sirka": 0.6,
      "hloubka": 1.655,
      "tvar": "rect",
      "uhel": 270.0,
      "zadni_strana": "north",
      "vyska": 0.9,
      "elevation": 0.0
    },
    {
      "id": "V6",
      "typ": "ElectricalAppliance",
      "podtyp": "IntegratedStove",
      "kategorie": "kuchyn",
      "stred": [
        3.6185289999999997,
        -0.7547600000000001
      ],
      "polygon": [
        [
          3.3166789999999997,
          -0.47476
        ],
        [
          3.920379,
          -0.47476
        ],
        [
          3.920379,
          -1.03476
        ],
        [
          3.3166789999999997,
          -1.03476
        ]
      ],
      "sirka": 0.604,
      "hloubka": 0.56,
      "tvar": "rect",
      "uhel": 0.0,
      "zadni_strana": null,
      "vyska": 0.9,
      "elevation": 0.0
    },
    {
      "id": "V7",
      "typ": "WallCabinet",
      "podtyp": null,
      "kategorie": "kuchyn",
      "stred": [
        2.7081470000000003,
        -0.604759
      ],
      "polygon": [
        [
          2.094847,
          -0.454759
        ],
        [
          3.321447,
          -0.454759
        ],
        [
          3.321447,
          -0.754759
        ],
        [
          2.094847,
          -0.754759
        ]
      ],
      "sirka": 1.227,
      "hloubka": 0.3,
      "tvar": "rect",
      "uhel": 0.0,
      "zadni_strana": "west",
      "vyska": 0.6,
      "elevation": 1.4
    },
    {
      "id": "V8",
      "typ": "DoubleSink",
      "podtyp": null,
      "kategorie": "kuchyn",
      "stred": [
        4.553524566171086,
        -1.737776335195888
      ],
      "polygon": [
        [
          4.828595,
          -1.7067290000000004
        ],
        [
          4.778595,
          -1.7067290000000004
        ],
        [
          4.778595,
          -1.3756290000000002
        ],
        [
          4.328595,
          -1.3756290000000002
        ],
        [
          4.328595,
          -1.6943327735849059
        ],
        [
          4.277595,
          -1.7454290000000001
        ],
        [
          4.3275950000000005,
          -1.7954290000000004
        ],
        [
          4.3275950000000005,
          -2.099829
        ],
        [
          4.777595,
          -2.099829
        ],
        [
          4.777595,
          -1.7667290000000002
        ],
        [
          4.828595,
          -1.7667290000000002
        ],
        [
          4.828595,
          -1.7067290000000004
        ]
      ],
      "sirka": 0.551,
      "hloubka": 0.724,
      "tvar": "polygon",
      "uhel": 270.0,
      "zadni_strana": null,
      "vyska": 0.9,
      "elevation": 0.0
    },
    {
      "id": "V9",
      "typ": "ElectricalAppliance",
      "podtyp": "Dishwasher",
      "kategorie": "kuchyn",
      "stred": [
        4.575564,
        -2.431532
      ],
      "polygon": [
        [
          4.875564,
          -2.156372
        ],
        [
          4.875564,
          -2.706692
        ],
        [
          4.275564,
          -2.706692
        ],
        [
          4.275564,
          -2.156372
        ]
      ],
      "sirka": 0.6,
      "hloubka": 0.55,
      "tvar": "rect",
      "uhel": 270.0,
      "zadni_strana": null,
      "vyska": 0.9,
      "elevation": 0.0
    },
    {
      "id": "V10",
      "typ": "WallCabinet",
      "podtyp": null,
      "kategorie": "kuchyn",
      "stred": [
        4.727595,
        -1.8794009999999997
      ],
      "polygon": [
        [
          4.877595,
          -1.052101
        ],
        [
          4.877595,
          -2.706701
        ],
        [
          4.5775950000000005,
          -2.706701
        ],
        [
          4.5775950000000005,
          -1.052101
        ]
      ],
      "sirka": 0.3,
      "hloubka": 1.655,
      "tvar": "rect",
      "uhel": 270.0,
      "zadni_strana": "north",
      "vyska": 0.6,
      "elevation": 1.4
    },
    {
      "id": "V11",
      "typ": "Shower",
      "podtyp": null,
      "kategorie": "koupelna",
      "stred": [
        5.014222643698685,
        -1.022151762369821
      ],
      "polygon": [
        [
          5.001130150259067,
          -1.1002652227979275
        ],
        [
          5.024783,
          -1.106716
        ],
        [
          5.007783,
          -1.094716
        ],
        [
          4.998253588235294,
          -1.0925983529411765
        ],
        [
          4.996783,
          -1.091716
        ],
        [
          4.9937019189189185,
          -1.0912024864864867
        ],
        [
          5.005894111111111,
          -1.0857160000000001
        ],
        [
          5.040783,
          -1.0857160000000001
        ],
        [
          5.040783,
          -1.070016
        ],
        [
          5.054783,
          -1.063716
        ],
        [
          5.040783,
          -1.0409426666666668
        ],
        [
          5.040783,
          -1.0384312317880795
        ],
        [
          5.127783,
          -0.968716
        ],
        [
          5.040783,
          -1.010698558139535
        ],
        [
          5.040783,
          -0.9821588571428572
        ],
        [
          5.059783,
          -0.941716
        ],
        [
          5.040783,
          -0.9763298613861386
        ],
        [
          5.040783,
          -0.9417160000000001
        ],
        [
          4.979783,
          -0.9417160000000001
        ],
        [
          4.979783,
          -1.0401346046511628
        ],
        [
          4.955783,
          -1.051716
        ],
        [
          4.957783,
          -1.053716
        ],
        [
          4.973783,
          -1.066716
        ],
        [
          4.979783,
          -1.0613160000000001
        ],
        [
          4.979783,
          -1.0780888813559322
        ],
        [
          4.974783,
          -1.090716
        ],
        [
          4.974783,
          -1.096567485148515
        ],
        [
          4.969830721179625,
          -1.1055894584450403
        ],
        [
          4.973783,
          -1.122716
        ],
        [
          4.999783,
          -1.111716
        ],
        [
          5.001130150259067,
          -1.1002652227979275
        ]
      ],
      "sirka": 0.172,
      "hloubka": 0.181,
      "tvar": "polygon",
      "uhel": 90.0,
      "zadni_strana": "north",
      "vyska": 0.97,
      "elevation": 1.35
    },
    {
      "id": "V12",
      "typ": "BaseCabinet",
      "podtyp": null,
      "kategorie": "kuchyn",
      "stred": [
        5.23277,
        -1.704824
      ],
      "polygon": [
        [
          4.9819700000000005,
          -1.966024
        ],
        [
          4.9819700000000005,
          -1.4436239999999998
        ],
        [
          5.483569999999999,
          -1.4436239999999998
        ],
        [
          5.483569999999999,
          -1.966024
        ]
      ],
      "sirka": 0.502,
      "hloubka": 0.522,
      "tvar": "rect",
      "uhel": 90.0,
      "zadni_strana": "north",
      "vyska": 0.05,
      "elevation": 1.05
    },
    {
      "id": "V13",
      "typ": "Sink",
      "podtyp": null,
      "kategorie": "koupelna",
      "stred": [
        5.258152255752403,
        -1.7015746898790634
      ],
      "polygon": [
        [
          5.02377,
          -1.670924
        ],
        [
          5.02377,
          -1.730924
        ],
        [
          5.07897,
          -1.730924
        ],
        [
          5.07897,
          -1.916024
        ],
        [
          5.4392700000000005,
          -1.916024
        ],
        [
          5.4392700000000005,
          -1.7174239999999998
        ],
        [
          5.44347,
          -1.7174239999999998
        ],
        [
          5.44347,
          -1.7554239999999999
        ],
        [
          5.4914700000000005,
          -1.7024239999999997
        ],
        [
          5.44347,
          -1.649424
        ],
        [
          5.44347,
          -1.6873239999999998
        ],
        [
          5.4392700000000005,
          -1.6873239999999998
        ],
        [
          5.4392700000000005,
          -1.4871240000000001
        ],
        [
          5.07897,
          -1.4871240000000001
        ],
        [
          5.07897,
          -1.670924
        ],
        [
          5.02377,
          -1.670924
        ]
      ],
      "sirka": 0.468,
      "hloubka": 0.429,
      "tvar": "polygon",
      "uhel": 90.0,
      "zadni_strana": "west",
      "vyska": 0.9,
      "elevation": 0.0
    },
    {
      "id": "V14",
      "typ": "Toilet",
      "podtyp": null,
      "kategorie": "koupelna",
      "stred": [
        5.479154111938982,
        -2.347929840275996
      ],
      "polygon": [
        [
          5.417153,
          -2.525817
        ],
        [
          5.679783,
          -2.5370470000000003
        ],
        [
          5.679783,
          -2.322747
        ],
        [
          5.679783,
          -2.115627
        ],
        [
          5.417153,
          -2.126907
        ],
        [
          5.1595830000000005,
          -2.5268170000000003
        ],
        [
          5.417153,
          -2.525817
        ]
      ],
      "sirka": 0.52,
      "hloubka": 0.421,
      "tvar": "polygon",
      "uhel": 90.0,
      "zadni_strana": "west",
      "vyska": 0.85,
      "elevation": 0.0
    },
    {
      "id": "V15",
      "typ": "ElectricalAppliance",
      "podtyp": "WashingMachine",
      "kategorie": "kuchyn",
      "stred": [
        6.651673000000001,
        -2.5161010000000004
      ],
      "polygon": [
        [
          6.891943,
          -2.209051
        ],
        [
          6.891943,
          -2.823151
        ],
        [
          6.411403,
          -2.823151
        ],
        [
          6.411403,
          -2.209051
        ]
      ],
      "sirka": 0.481,
      "hloubka": 0.614,
      "tvar": "rect",
      "uhel": 270.0,
      "zadni_strana": null,
      "vyska": 0.9,
      "elevation": 0.0
    },
    {
      "id": "V16",
      "typ": "Misc",
      "podtyp": null,
      "kategorie": "ostatni",
      "stred": [
        5.574033000000001,
        -1.0799180000000002
      ],
      "polygon": [
        [
          4.925033,
          -1.404418
        ],
        [
          5.898533,
          -1.404418
        ],
        [
          5.898533,
          -0.4309180000000001
        ],
        [
          4.925033,
          -1.404418
        ]
      ],
      "sirka": 0.973,
      "hloubka": 0.973,
      "tvar": "rect",
      "uhel": 0.0,
      "zadni_strana": null,
      "vyska": 2.0,
      "elevation": 0.0
    },
    {
      "id": "V17",
      "typ": "CoatCloset",
      "podtyp": null,
      "kategorie": "uloziste",
      "stred": [
        6.352975999999999,
        -6.701461000000001
      ],
      "polygon": [
        [
          6.526776,
          -6.060961
        ],
        [
          6.526776,
          -7.341961
        ],
        [
          6.179176,
          -7.341961
        ],
        [
          6.179176,
          -6.060961
        ]
      ],
      "sirka": 0.348,
      "hloubka": 1.281,
      "tvar": "rect",
      "uhel": 270.0,
      "zadni_strana": null,
      "vyska": 2.0,
      "elevation": 0.0
    },
    {
      "id": "V18",
      "typ": "CoatCloset",
      "podtyp": null,
      "kategorie": "uloziste",
      "stred": [
        0.9268549999999999,
        -8.336167999999999
      ],
      "polygon": [
        [
          0.698905,
          -9.180218
        ],
        [
          0.698905,
          -7.4921180000000005
        ],
        [
          1.154805,
          -7.4921180000000005
        ],
        [
          1.154805,
          -9.180218
        ]
      ],
      "sirka": 0.456,
      "hloubka": 1.688,
      "tvar": "rect",
      "uhel": 90.0,
      "zadni_strana": null,
      "vyska": 2.0,
      "elevation": 0.0
    },
    {
      "id": "V19",
      "typ": "CoatCloset",
      "podtyp": null,
      "kategorie": "uloziste",
      "stred": [
        2.463733,
        -8.100741999999999
      ],
      "polygon": [
        [
          2.7098329999999997,
          -7.491992000000001
        ],
        [
          2.7098329999999997,
          -8.709492000000001
        ],
        [
          2.2176329999999997,
          -8.709492000000001
        ],
        [
          2.2176329999999997,
          -7.491992000000001
        ]
      ],
      "sirka": 0.492,
      "hloubka": 1.218,
      "tvar": "rect",
      "uhel": 270.0,
      "zadni_strana": null,
      "vyska": 2.0,
      "elevation": 0.0
    },
    {
      "id": "V20",
      "typ": "Closet",
      "podtyp": null,
      "kategorie": "uloziste",
      "stred": [
        1.6855849999999999,
        -8.942567
      ],
      "polygon": [
        [
          2.216385,
          -9.180217
        ],
        [
          1.154785,
          -9.180217
        ],
        [
          1.154785,
          -8.704917
        ],
        [
          2.216385,
          -8.704917
        ]
      ],
      "sirka": 1.062,
      "hloubka": 0.475,
      "tvar": "rect",
      "uhel": 180.0,
      "zadni_strana": null,
      "vyska": 2.0,
      "elevation": 0.0
    }
  ],
  "sloupy": [
    {
      "id": "C1",
      "stred": [
        4.5906,
        -0.7289
      ],
      "polygon": [
        [
          4.2735,
          -1.0521
        ],
        [
          4.2735,
          -0.4057
        ],
        [
          4.9077,
          -0.4057
        ],
        [
          4.9077,
          -1.0521
        ]
      ],
      "sirka": 0.634,
      "hloubka": 0.646
    },
    {
      "id": "C2",
      "stred": [
        2.4846500000000002,
        -8.9791
      ],
      "polygon": [
        [
          2.2096,
          -8.7096
        ],
        [
          2.2096,
          -9.2486
        ],
        [
          2.7597000000000005,
          -9.2486
        ],
        [
          2.7597000000000005,
          -8.7096
        ]
      ],
      "sirka": 0.55,
      "hloubka": 0.539
    }
  ],
  "zabradli": [
    {
      "id": "R1",
      "polygon": [
        [
          14.0259,
          -0.4509
        ],
        [
          14.0259,
          -4.1284
        ],
        [
          13.925899999999999,
          -4.1284
        ],
        [
          13.925899999999999,
          -0.4509
        ]
      ],
      "delka": 3.678
    }
  ],
  "schodiste": [],
  "metadata": {
    "source": "pudorys",
    "original_id": "9311",
    "viewbox": "0 0 1483.8950538635254 933.0200414657593",
    "width": 1483.8950538635254,
    "height": 933.0200414657593,
    "scale_px_to_m": 0.01,
    "wall_outline": [
      {
        "exterior": [
          [
            0.4509,
            -0.3019
          ],
          [
            0.4509,
            -9.2552
          ],
          [
            0.5749000000000001,
            -9.2552
          ],
          [
            0.5749000000000001,
            -9.3302
          ],
          [
            2.7848,
            -9.3302
          ],
          [
            2.7848,
            -9.2552
          ],
          [
            2.8598000000000003,
            -9.2552
          ],
          [
            2.8598000000000003,
            -7.492000000000001
          ],
          [
            6.6024,
            -7.492000000000001
          ],
          [
            6.6024,
            -7.417000000000001
          ],
          [
            6.6774000000000004,
            -7.417000000000001
          ],
          [
            6.6774000000000004,
            -4.3084
          ],
          [
            12.28785,
            -4.3084
          ],
          [
            12.28785,
            -4.2334
          ],
          [
            12.4067,
            -4.2334
          ],
          [
            12.4067,
            -4.3084
          ],
          [
            14.0259,
            -4.3084
          ],
          [
            14.0259,
            -4.1284
          ],
          [
            12.4067,
            -4.1284
          ],
          [
            12.4067,
            -0.4509
          ],
          [
            14.0259,
            -0.4509
          ],
          [
            14.0259,
            -0.29090000000000005
          ],
          [
            12.4067,
            -0.29090000000000005
          ],
          [
            12.4067,
            -0.3019
          ],
          [
            12.28785,
            -0.3019
          ],
          [
            12.28785,
            -0.1529
          ],
          [
            0.5749000000000001,
            -0.1529
          ],
          [
            0.5749000000000001,
            -0.3019
          ]
        ],
        "holes": [
          [
            [
              12.169,
              -4.158399999999999
            ],
            [
              6.994199999999999,
              -4.158399999999999
            ],
            [
              6.994199999999999,
              -0.4509
            ],
            [
              12.169,
              -0.4509
            ]
          ],
          [
            [
              4.9798,
              -2.9122000000000003
            ],
            [
              4.9798,
              -0.4509
            ],
            [
              6.8942,
              -0.4509
            ],
            [
              6.8942,
              -2.9122000000000003
            ]
          ],
          [
            [
              4.9798,
              -7.3420000000000005
            ],
            [
              4.9798,
              -3.0122000000000004
            ],
            [
              6.8942,
              -3.0122000000000004
            ],
            [
              6.8942,
              -4.158399999999999
            ],
            [
              6.6024,
              -4.158399999999999
            ],
            [
              6.6024,
              -4.2334
            ],
            [
              6.5274,
              -4.2334
            ],
            [
              6.5274,
              -7.3420000000000005
            ]
          ],
          [
            [
              4.8798,
              -4.1436
            ],
            [
              0.6989,
              -4.1436
            ],
            [
              0.6989,
              -0.4509
            ],
            [
              4.8798,
              -0.4509
            ]
          ],
          [
            [
              4.8798,
              -7.3420000000000005
            ],
            [
              2.7848,
              -7.3420000000000005
            ],
            [
              2.7848,
              -7.417000000000001
            ],
            [
              2.7098000000000004,
              -7.417000000000001
            ],
            [
              2.7098000000000004,
              -7.3420000000000005
            ],
            [
              0.6989,
              -7.3420000000000005
            ],
            [
              0.6989,
              -4.306
            ],
            [
              4.8798,
              -4.306
            ]
          ],
          [
            [
              0.6989,
              -7.492000000000001
            ],
            [
              2.7098000000000004,
              -7.492000000000001
            ],
            [
              2.7098000000000004,
              -9.1802
            ],
            [
              0.6989,
              -9.1802
            ]
          ]
        ]
      }
    ],
    "plocha_budovy_m2": 19.2,
    "ma_obvod": true,
    "stats": {
      "pocet_sten": 15,
      "pocet_uzlu": 22,
      "pocet_otvoru": 11,
      "pocet_prostoru": 7,
      "pocet_vybaveni": 20,
      "pocet_sloupu": 2,
      "pocet_zabradli": 1,
      "pocet_schodist": 0,
      "typy_sten": {
        "obvodova": 1,
        "nosna": 2,
        "pricka": 12
      },
      "typy_prostoru": {
        "Outdoor": 1,
        "LivingRoom": 1,
        "Kitchen": 1,
        "Bedroom": 1,
        "Undefined": 1,
        "Bath": 1,
        "Closet/WalkIn": 1
      },
      "kategorie_vybaveni": {
        "ostatni": 2,
        "uloziste": 5,
        "kuchyn": 10,
        "koupelna": 3
      }
    }
  }
}